anythreejs/__init__.py
anythreejs/core/__init__.py
anythreejs/core/base.py
anythreejs/core/buffer.py
anythreejs/core/camera.py
anythreejs/core/controls.py
anythreejs/core/geometry.py
anythreejs/core/helpers.py
anythreejs/core/lights.py
anythreejs/core/material.py
anythreejs/core/objects.py
anythreejs/core/scene.py
anythreejs/core/textures.py
anythreejs/py.typed
anythreejs/renderer.py
anythreejs/widget.css
anythreejs/widget.js
anythreejs-0.0.1.dist-info/licenses/LICENSE
anythreejs-0.0.1.dist-info/WHEEL
anythreejs-0.0.1.dist-info/METADATA
anythreejs-0.0.1.dist-info/RECORD
