Metadata-Version: 2.4
Name: anythreejs
Version: 0.0.1
Summary: Anywidget wrapper for three.js
Keywords: jupyter,widgets,threejs,3d,visualization,anywidget
Author: Mridul Seth
Author-email: Mridul Seth <mail@mriduls.com>
License-Expression: BSD-3-Clause
License-File: LICENSE
Classifier: Development Status :: 3 - Alpha
Classifier: Framework :: Jupyter
Classifier: Intended Audience :: Developers
Classifier: Intended Audience :: Science/Research
Classifier: License :: OSI Approved :: BSD License
Classifier: Programming Language :: Python :: 3.11
Classifier: Programming Language :: Python :: 3.12
Classifier: Programming Language :: Python :: 3.13
Requires-Dist: anywidget>=0.9.21
Requires-Dist: numpy>=2
Requires-Dist: traitlets>=5.14.3
Requires-Python: >=3.11
Project-URL: Homepage, https://github.com/MridulS/anythreejs
Project-URL: Repository, https://github.com/MridulS/anythreejs
